simiq/__init__.py
simiq-0.0.dev0.dist-info/METADATA
simiq-0.0.dev0.dist-info/WHEEL
simiq-0.0.dev0.dist-info/top_level.txt
simiq-0.0.dev0.dist-info/RECORD
