Metadata-Version: 2.4
Name: simiq
Version: 0.0.dev0
Summary: Simulation Insights AI-Agent.
Author-email: Hans Bouwmeester <hans.bouwmeester@icloud.com>, Asav Gandhi <asavgandhi01@gmail.com>
Classifier: Programming Language :: Python
Classifier: Programming Language :: Python :: 3.10
Classifier: Programming Language :: Python :: 3.11
Classifier: Programming Language :: Python :: 3.12
Classifier: Programming Language :: Python :: 3.13
Classifier: Programming Language :: Python :: Implementation :: CPython
Classifier: Programming Language :: Python :: Implementation :: PyPy
Requires-Python: >=3.10
